packagedquestgenforlambda/__init__.py
packagedquestgenforlambda/main.py
packagedquestgenforlambda/encoding/__init__.py
packagedquestgenforlambda/encoding/encoding.py
packagedquestgenforlambda/mcq/__init__.py
packagedquestgenforlambda/mcq/mcq.py
packagedquestgenforlambda-1.0.3.dist-info/LICENSE
packagedquestgenforlambda-1.0.3.dist-info/METADATA
packagedquestgenforlambda-1.0.3.dist-info/WHEEL
packagedquestgenforlambda-1.0.3.dist-info/top_level.txt
packagedquestgenforlambda-1.0.3.dist-info/RECORD
