Metadata-Version: 2.1
Name: packagedquestgenforlambda
Version: 1.0.3
Summary: Question generator from any text
Home-page: https://github.com/ramsrigouthamg/packagedquestgenforlambda.ai
Author: packagedquestgenforlambda contributors
Author-email: vaibhavtiwarifu@gmail.com
License: UNKNOWN
Platform: UNKNOWN
License-File: LICENSE
Requires-Dist: torch (==1.9.0)
Requires-Dist: transformers (==3.0.2)
Requires-Dist: pytorch-lightning (==0.8.1)
Requires-Dist: sense2vec (==1.0.3)
Requires-Dist: strsim (==0.0.3)
Requires-Dist: six (==1.15.0)
Requires-Dist: networkx (==2.4.0)
Requires-Dist: numpy
Requires-Dist: scipy
Requires-Dist: scikit-learn
Requires-Dist: unidecode (==1.1.1)
Requires-Dist: future (==0.18.2)
Requires-Dist: joblib (==0.14.1)
Requires-Dist: spacy (==2.2.4)
Requires-Dist: pytz (==2020.1)
Requires-Dist: python-dateutil (==2.8.1)
Requires-Dist: boto3 (==1.14.40)
Requires-Dist: flashtext (==2.7)
Requires-Dist: pandas
